[
  {
    "full_name": "postcss/autoprefixer",
    "stargazers_count": 20438,
    "open_issues_count": 33,
    "forks_count": 1263
  },
  {
    "full_name": "argyleink/gui-challenges",
    "stargazers_count": 1497,
    "open_issues_count": 9,
    "forks_count": 199
  },
  {
    "full_name": "MarcAnt01/Fluent-Screen-Recorder",
    "stargazers_count": 385,
    "open_issues_count": 27,
    "forks_count": 27
  },
  {
    "full_name": "docker/login-action",
    "stargazers_count": 469,
    "open_issues_count": 7,
    "forks_count": 100
  },
  {
    "full_name": "docker/build-push-action",
    "stargazers_count": 2483,
    "open_issues_count": 30,
    "forks_count": 368
  },
  {
    "full_name": "marceloprates/prettymaps",
    "stargazers_count": 8293,
    "open_issues_count": 43,
    "forks_count": 383
  },
  {
    "full_name": "microsoft/vscode-pull-request-github",
    "stargazers_count": 1872,
    "open_issues_count": 344,
    "forks_count": 426
  },
  {
    "full_name": "golang/go",
    "stargazers_count": 101430,
    "open_issues_count": 7792,
    "forks_count": 15073
  },
  {
    "full_name": "hoppscotch/hoppscotch",
    "stargazers_count": 44852,
    "open_issues_count": 88,
    "forks_count": 3032
  },
  {
    "full_name": "github-php/sponsors",
    "stargazers_count": 100,
    "open_issues_count": 12,
    "forks_count": 6
  },
  {
    "full_name": "microsoft/msquic",
    "stargazers_count": 2876,
    "open_issues_count": 102,
    "forks_count": 347
  },
  {
    "full_name": "uraimo/run-on-arch-action",
    "stargazers_count": 376,
    "open_issues_count": 30,
    "forks_count": 80
  },
  {
    "full_name": "chromium/chromium",
    "stargazers_count": 12503,
    "open_issues_count": 54,
    "forks_count": 4783
  },
  {
    "full_name": "actions/checkout",
    "stargazers_count": 2833,
    "open_issues_count": 294,
    "forks_count": 939
  },
  {
    "full_name": "andresz1/size-limit-action",
    "stargazers_count": 321,
    "open_issues_count": 17,
    "forks_count": 43
  },
  {
    "full_name": "jshttp/mime-db",
    "stargazers_count": 831,
    "open_issues_count": 13,
    "forks_count": 217
  },
  {
    "full_name": "mTvare6/hello-world.rs",
    "stargazers_count": 2296,
    "open_issues_count": 92,
    "forks_count": 71
  },
  {
    "full_name": "gitpod-io/leeway",
    "stargazers_count": 115,
    "open_issues_count": 17,
    "forks_count": 17
  },
  {
    "full_name": "livewire-ui/modal",
    "stargazers_count": 697,
    "open_issues_count": 7,
    "forks_count": 76
  },
  {
    "full_name": "mrousavy/react-native-mmkv",
    "stargazers_count": 2195,
    "open_issues_count": 29,
    "forks_count": 102
  },
  {
    "full_name": "expo/config-plugins",
    "stargazers_count": 155,
    "open_issues_count": 20,
    "forks_count": 30
  },
  {
    "full_name": "gitpod-io/roadmap",
    "stargazers_count": 40,
    "open_issues_count": 11,
    "forks_count": 10
  },
  {
    "full_name": "vvo/next-iron-session",
    "stargazers_count": 1647,
    "open_issues_count": 36,
    "forks_count": 179
  },
  {
    "full_name": "quilljs/quill",
    "stargazers_count": 33051,
    "open_issues_count": 1239,
    "forks_count": 2831
  },
  {
    "full_name": "systemd/systemd",
    "stargazers_count": 9781,
    "open_issues_count": 1885,
    "forks_count": 2988
  },
  {
    "full_name": "protocolbuffers/protobuf",
    "stargazers_count": 55277,
    "open_issues_count": 875,
    "forks_count": 14242
  },
  {
    "full_name": "swc-project/swc",
    "stargazers_count": 22889,
    "open_issues_count": 249,
    "forks_count": 735
  },
  {
    "full_name": "CZ-NIC/knot-resolver",
    "stargazers_count": 253,
    "open_issues_count": 1,
    "forks_count": 45
  },
  {
    "full_name": "delta-craft/delta-craft-portal",
    "stargazers_count": 2,
    "open_issues_count": 12,
    "forks_count": 1
  },
  {
    "full_name": "tauri-apps/tauri",
    "stargazers_count": 46174,
    "open_issues_count": 181,
    "forks_count": 1146
  }
]